taskw/__init__.py
taskw/exceptions.py
taskw/task.py
taskw/taskrc.py
taskw/utils.py
taskw/warrior.py
taskw/fields/__init__.py
taskw/fields/annotationarray.py
taskw/fields/array.py
taskw/fields/base.py
taskw/fields/choice.py
taskw/fields/commaseparateduuid.py
taskw/fields/date.py
taskw/fields/duration.py
taskw/fields/numeric.py
taskw/fields/string.py
taskw/fields/uuid.py
taskw/test/__init__.py
taskw/test/test_datas.py
taskw/test/test_fields.py
taskw/test/test_recursive.py
taskw/test/test_task.py
taskw/test/test_taskrc.py
taskw/test/test_utils.py
taskw/test/test_warrior.py
taskw/test/data/default.taskrc
taskw/test/data/empty.taskrc
taskw/test/data/included.taskrc
taskw-2.0.0.dist-info/LICENSE.txt
taskw-2.0.0.dist-info/METADATA
taskw-2.0.0.dist-info/WHEEL
taskw-2.0.0.dist-info/entry_points.txt
taskw-2.0.0.dist-info/top_level.txt
taskw-2.0.0.dist-info/RECORD
