Metadata-Version: 2.1
Name: taskw
Version: 2.0.0
Summary: Python bindings for your taskwarrior database
Home-page: http://github.com/ralphbean/taskw
Author: Ralph Bean
Author-email: ralph.bean@gmail.com
License: GPLv3+
Keywords: taskwarrior task
Platform: UNKNOWN
Classifier: Development Status :: 5 - Production/Stable
Classifier: Programming Language :: Python :: 3
Classifier: Programming Language :: Python :: 3.4
Classifier: Programming Language :: Python :: 3.5
Classifier: Programming Language :: Python :: 3.6
Classifier: Programming Language :: Python :: 3.7
Classifier: Programming Language :: Python :: 3.8
Classifier: License :: OSI Approved :: GNU General Public License (GPL)
Classifier: Intended Audience :: Developers
License-File: LICENSE.txt
Requires-Dist: kitchen
Requires-Dist: python-dateutil
Requires-Dist: pytz
